certsrv/__init__.py
certsrv/certsrv.py
certsrv/errors.py
certsrv/utils.py
certsrv/version.py
python_certsrv-1.0.0.dist-info/LICENSE
python_certsrv-1.0.0.dist-info/METADATA
python_certsrv-1.0.0.dist-info/WHEEL
python_certsrv-1.0.0.dist-info/top_level.txt
python_certsrv-1.0.0.dist-info/RECORD
