Metadata-Version: 2.1
Name: python-certsrv
Version: 1.0.0
Summary: A Python client for the Active Directory Certificate Service Web Enrollment.
Home-page: https://github.com/degagne/python-certsrv
Author: Deric Degagne
Author-email: deric.degagne@gmail.com
License: MIT
Keywords: ad adcs certsrv pki certificate
Platform: UNKNOWN
Classifier: Development Status :: 5 - Production/Stable
Classifier: Intended Audience :: Developers
Classifier: Intended Audience :: System Administrators
Classifier: Programming Language :: Python :: 3.6
Classifier: License :: OSI Approved :: MIT License
Classifier: Topic :: Internet :: WWW/HTTP
Classifier: Topic :: Security
Classifier: Topic :: System :: Systems Administration
Requires-Python: >=3.6
License-File: LICENSE
Requires-Dist: requests
Requires-Dist: requests-ntlm3
